petdeface/README.md
petdeface/__init__.py
petdeface/mideface.py
petdeface/pet.py
petdeface/petdeface.py
pyproject.toml
petdeface-0.2.2.dist-info/METADATA
petdeface-0.2.2.dist-info/WHEEL
petdeface-0.2.2.dist-info/entry_points.txt
petdeface-0.2.2.dist-info/RECORD
