Metadata-Version: 2.1
Name: petdeface
Version: 0.2.2
Summary: A nipype PET and MR defacing pipeline for BIDS datasets utilizing FreeSurfer's MiDeFace.
License: MIT
Author: Martin Nørgaard
Author-email: martin.noergaard@nru.dk
Requires-Python: >=3.10,<4.0
Classifier: License :: OSI Approved :: MIT License
Classifier: Programming Language :: Python :: 3
Classifier: Programming Language :: Python :: 3.10
Classifier: Programming Language :: Python :: 3.11
Classifier: Programming Language :: Python :: 3.12
Requires-Dist: niworkflows (>=1.11.0,<2.0.0)
Requires-Dist: petutils (>=0.0.1,<0.0.2)
Requires-Dist: setuptools (>=68.1.2,<69.0.0)
